restio/__init__.py
restio/cache.py
restio/dao.py
restio/event.py
restio/graph.py
restio/model.py
restio/query.py
restio/state.py
restio/transaction.py
restio-0.3.0.dist-info/LICENSE
restio-0.3.0.dist-info/METADATA
restio-0.3.0.dist-info/WHEEL
restio-0.3.0.dist-info/top_level.txt
restio-0.3.0.dist-info/RECORD
