Metadata-Version: 2.1
Name: restio
Version: 0.3.0
Summary: restio Framework
Home-page: https://github.com/eduardostarling/restio.git
Author: Eduardo Starling
Author-email: edmstar@gmail.com
License: UNKNOWN
Project-URL: Source Code, https://github.com/eduardostarling/restio.git
Platform: UNKNOWN
Classifier: Programming Language :: Python :: 3
Classifier: License :: OSI Approved :: MIT License
Classifier: Operating System :: OS Independent
Requires-Python: >=3.7
